bass/__init__.py
bass/common.py
bass/config.py
bass/event.py
bass/layout.py
bass/markup.py
bass/server.py
bass/setting.py
bass/site.py
bass/tree.py
bass/__pycache__/__init__.cpython-34.pyc
bass/__pycache__/common.cpython-34.pyc
bass/__pycache__/config.cpython-34.pyc
bass/__pycache__/event.cpython-34.pyc
bass/__pycache__/layout.cpython-34.pyc
bass/__pycache__/markup.cpython-34.pyc
bass/__pycache__/server.cpython-34.pyc
bass/__pycache__/setting.cpython-34.pyc
bass/__pycache__/site.cpython-34.pyc
bass/__pycache__/tree.cpython-34.pyc
bass-1.3.0.data/scripts/bass
bass-1.3.0.dist-info/LICENSE
bass-1.3.0.dist-info/METADATA
bass-1.3.0.dist-info/WHEEL
bass-1.3.0.dist-info/top_level.txt
bass-1.3.0.dist-info/RECORD
